gml/__init__.py
gml/compile.py
gml_api-0.0.1.dist-info/METADATA
gml_api-0.0.1.dist-info/WHEEL
gml_api-0.0.1.dist-info/top_level.txt
gml_api-0.0.1.dist-info/RECORD
